setup.py
gmm_lbd/__init__.py
gmm_lbd/data_manager.py
gmm_lbd/gmm.py
gmm_lbd/operations.py
gmm_lbd.egg-info/PKG-INFO
gmm_lbd.egg-info/SOURCES.txt
gmm_lbd.egg-info/dependency_links.txt
gmm_lbd.egg-info/pbr.json
gmm_lbd.egg-info/requires.txt
gmm_lbd.egg-info/top_level.txt