Metadata-Version: 1.1
Name: gmm-lbd
Version: 0.0.4
Summary: Some gmm regression experiments for learning by demonstration
Home-page: https://github.com/show0k/gmm-lbd
Author: Théo Segonds
Author-email: theo.segonds@inria.fr
License: MIT
Platform: UNKNOWN
Classifier: Programming Language :: Python
Classifier: Programming Language :: Python :: 2.7
